setup.py
vmcontroller/__init__.py
vmcontroller.common.egg-info/PKG-INFO
vmcontroller.common.egg-info/SOURCES.txt
vmcontroller.common.egg-info/dependency_links.txt
vmcontroller.common.egg-info/namespace_packages.txt
vmcontroller.common.egg-info/not-zip-safe
vmcontroller.common.egg-info/requires.txt
vmcontroller.common.egg-info/top_level.txt
vmcontroller/common/BaseStompEngine.py
vmcontroller/common/BaseWord.py
vmcontroller/common/CommandExecuter.py
vmcontroller/common/EntityDescriptor.py
vmcontroller/common/FileTransfer.py
vmcontroller/common/StompProtocol.py
vmcontroller/common/StompProtocolFactory.py
vmcontroller/common/__init__.py
vmcontroller/common/destinations.py
vmcontroller/common/exceptions.py
vmcontroller/common/support.py